prediprot_imports/__init__.py
prediprot_imports/prediprot_classes.py
prediprot_imports/prediprot_functions.py
prediprot_imports/prediprot_optimize.py
PrediProt_imports-1.0.0.dist-info/LICENSE
PrediProt_imports-1.0.0.dist-info/METADATA
PrediProt_imports-1.0.0.dist-info/WHEEL
PrediProt_imports-1.0.0.dist-info/top_level.txt
PrediProt_imports-1.0.0.dist-info/RECORD
